reporting/__init__.py
reporting/admin.py
reporting/apps.py
reporting/context_processors.py
reporting/lib.py
reporting/urls.py
reporting/views.py
reporting/migrations/__init__.py
reporting/models/__init__.py
reporting/models/dashboard.py
reporting/models/dataset.py
reporting/models/report.py
reporting/templates/__init__.py
reporting/templates/reporting/aside.html
reporting/templates/reporting/base.html
reporting/templates/reporting/dashboard_detail.html
reporting/templates/reporting/dashboard_report.html
reporting/templates/reporting/footer.html
reporting/templates/reporting/header.html
reporting/templates/reporting/index.html
reporting/templates/reporting/list.html
reporting/templates/reporting/report_detail.html
reporting/templatetags/__init__.py
reporting/templatetags/gravatar.py
reporting/templatetags/report.py
reporting/templatetags/uuid.py
reporting/tests/__init__.py
reporting/tests/test_lib.py
reporting/tests/test_models.py
reporting/tests/test_views.py
django_bi-1.0.0.dist-info/LICENSE
django_bi-1.0.0.dist-info/METADATA
django_bi-1.0.0.dist-info/WHEEL
django_bi-1.0.0.dist-info/top_level.txt
django_bi-1.0.0.dist-info/RECORD
